[
    {
        "meeting_key": 1259,
        "session_key": 10033,
        "driver_number": 12,
        "i1_speed": 207,
        "i2_speed": 183,
        "st_speed": 313,
        "date_start": null,
        "lap_duration": null,
        "is_pit_out_lap": false,
        "duration_sector_1": null,
        "duration_sector_2": 35.389,
        "duration_sector_3": 26.219,
        "segments_sector_1": [
            2064,
            2049,
            2049,
            2051,
            2049,
            2049,
            2049,
            2049,
            2049
        ],
        "segments_sector_2": [
            2049,
            2049,
            2049,
            2049,
            2049,
            2049,
            2049,
            2049,
            2049
        ],
        "segments_sector_3": [
            2048,
            2048,
            2048,
            2048,
            2048,
            2048,
            2048,
            2048
        ],
        "lap_number": 1
    },
    {
        "meeting_key": 1259,
        "session_key": 10033,
        "driver_number": 12,
        "i1_speed": 209,
        "i2_speed": 130,
        "st_speed": 246,
        "date_start": "2025-05-04T20:05:19.398000+00:00",
        "lap_duration": 112.276,
        "is_pit_out_lap": false,
        "duration_sector_1": 31.837,
        "duration_sector_2": 47.99,
        "duration_sector_3": 32.449,
        "segments_sector_1": [
            2049,
            2051,
            2049,
            2049,
            2049,
            2049,
            2049,
            2049,
            2048
        ],
        "segments_sector_2": [
            2049,
            2048,
            2048,
            2049,
            2048,
            2048,
            2048,
            2048,
            2048
        ],
        "segments_sector_3": [
            2048,
            2048,
            2048,
            2048,
            2048,
            2048,
            2048,
            2048
        ],
        "lap_number": 2
    },
    {
        "meeting_key": 1259,
        "session_key": 10033,
        "driver_number": 12,
        "i1_speed": 139,
        "i2_speed": 164,
        "st_speed": 192,
        "date_start": "2025-05-04T20:07:11.787000+00:00",
        "lap_duration": 124.905,
        "is_pit_out_lap": false,
        "duration_sector_1": 43.447,
        "duration_sector_2": 49.061,
        "duration_sector_3": 32.397,
        "segments_sector_1": [
            2048,
            2048,
            2048,
            2048,
            2048,
            2048,
            2048,
            2048,
            2048
        ],
        "segments_sector_2": [
            2048,
            2048,
            2048,
            2048,
            2048,
            2048,
            2048,
            2048,
            2048
        ],
        "segments_sector_3": [
            2049,
            2049,
            2049,
            2049,
            2049,
            2048,
            2049,
            2049
        ],
        "lap_number": 3
    },
    {
        "meeting_key": 1259,
        "session_key": 10033,
        "driver_number": 12,
        "i1_speed": 209,
        "i2_speed": 181,
        "st_speed": 324,
        "date_start": "2025-05-04T20:09:16.676000+00:00",
        "lap_duration": 93.016,
        "is_pit_out_lap": false,
        "duration_sector_1": 31.385,
        "duration_sector_2": 35.73,
        "duration_sector_3": 25.901,
        "segments_sector_1": [
            2049,
            2048,
            2049,
            2049,
            2049,
            2049,
            2048,
            2049,
            2048
        ],
        "segments_sector_2": [
            2048,
            2048,
            2049,
            2048,
            2048,
            2049,
            2048,
            2048,
            2048
        ],
        "segments_sector_3": [
            2049,
            2048,
            2048,
            2048,
            2049,
            2048,
            2048,
            2048
        ],
        "lap_number": 4
    },
    {
        "meeting_key": 1259,
        "session_key": 10033,
        "driver_number": 12,
        "i1_speed": 208,
        "i2_speed": 184,
        "st_speed": 317,
        "date_start": "2025-05-04T20:10:49.741000+00:00",
        "lap_duration": 92.859,
        "is_pit_out_lap": false,
        "duration_sector_1": 31.587,
        "duration_sector_2": 35.216,
        "duration_sector_3": 26.056,
        "segments_sector_1": [
            null,
            2048,
            2048,
            2049,
            2049,
            2048,
            2048,
            2049,
            2048
        ],
        "segments_sector_2": [
            2049,
            2049,
            2049,
            2049,
            2048,
            2049,
            2048,
            2049,
            2048
        ],
        "segments_sector_3": [
            2049,
            2048,
            2048,
            2048,
            2048,
            2048,
            2048,
            2048
        ],
        "lap_number": 5
    },
    {
        "meeting_key": 1259,
        "session_key": 10033,
        "driver_number": 12,
        "i1_speed": 204,
        "i2_speed": 184,
        "st_speed": 316,
        "date_start": "2025-05-04T20:12:22.555000+00:00",
        "lap_duration": 92.883,
        "is_pit_out_lap": false,
        "duration_sector_1": 31.428,
        "duration_sector_2": 35.276,
        "duration_sector_3": 26.179,
        "segments_sector_1": [
            2048,
            2048,
            2048,
            2049,
            2049,
            2048,
            2049,
            2048,
            2048
        ],
        "segments_sector_2": [
            2048,
            2048,
            2048,
            2048,
            2049,
            2048,
            2048,
            2048,
            2048
        ],
        "segments_sector_3": [
            2048,
            2048,
            2048,
            2048,
            2048,
            2048,
            2048,
            2048
        ],
        "lap_number": 6
    },
    {
        "meeting_key": 1259,
        "session_key": 10033,
        "driver_number": 12,
        "i1_speed": 206,
        "i2_speed": 181,
        "st_speed": 314,
        "date_start": "2025-05-04T20:13:55.371000+00:00",
        "lap_duration": 93.029,
        "is_pit_out_lap": false,
        "duration_sector_1": 31.467,
        "duration_sector_2": 35.391,
        "duration_sector_3": 26.171,
        "segments_sector_1": [
            null,
            2048,
            2048,
            2048,
            2048,
            2048,
            2048,
            2048,
            2048
        ],
        "segments_sector_2": [
            2048,
            2048,
            2048,
            2048,
            2048,
            2048,
            2048,
            2049,
            2048
        ],
        "segments_sector_3": [
            2048,
            2048,
            2048,
            2048,
            2048,
            2048,
            2048,
            2048
        ],
        "lap_number": 7
    },
    {
        "meeting_key": 1259,
        "session_key": 10033,
        "driver_number": 12,
        "i1_speed": 205,
        "i2_speed": 180,
        "st_speed": 317,
        "date_start": "2025-05-04T20:15:28.398000+00:00",
        "lap_duration": 92.945,
        "is_pit_out_lap": false,
        "duration_sector_1": 31.534,
        "duration_sector_2": 35.278,
        "duration_sector_3": 26.133,
        "segments_sector_1": [
            null,
            2048,
            2048,
            2048,
            2048,
            2048,
            2048,
            2048,
            2048
        ],
        "segments_sector_2": [
            2048,
            2048,
            2048,
            2048,
            2048,
            2048,
            2048,
            2049,
            2048
        ],
        "segments_sector_3": [
            2048,
            2049,
            2049,
            2048,
            2048,
            2048,
            2049,
            2048
        ],
        "lap_number": 8
    },
    {
        "meeting_key": 1259,
        "session_key": 10033,
        "driver_number": 12,
        "i1_speed": 207,
        "i2_speed": 180,
        "st_speed": 313,
        "date_start": "2025-05-04T20:17:01.364000+00:00",
        "lap_duration": 93.684,
        "is_pit_out_lap": false,
        "duration_sector_1": 31.466,
        "duration_sector_2": 36.056,
        "duration_sector_3": 26.162,
        "segments_sector_1": [
            null,
            2048,
            2048,
            2048,
            2048,
            2048,
            2049,
            2048,
            2048
        ],
        "segments_sector_2": [
            2048,
            2048,
            2048,
            2048,
            2048,
            2048,
            2048,
            2048,
            2048
        ],
        "segments_sector_3": [
            2048,
            2048,
            2048,
            2048,
            2048,
            2048,
            2048,
            2048
        ],
        "lap_number": 9
    },
    {
        "meeting_key": 1259,
        "session_key": 10033,
        "driver_number": 12,
        "i1_speed": 205,
        "i2_speed": 180,
        "st_speed": 316,
        "date_start": "2025-05-04T20:18:35.103000+00:00",
        "lap_duration": 93.004,
        "is_pit_out_lap": false,
        "duration_sector_1": 31.519,
        "duration_sector_2": 35.285,
        "duration_sector_3": 26.2,
        "segments_sector_1": [
            null,
            2048,
            2048,
            2048,
            2048,
            2048,
            2048,
            2048,
            2048
        ],
        "segments_sector_2": [
            2048,
            2049,
            2049,
            2049,
            2048,
            2048,
            2048,
            2048,
            2048
        ],
        "segments_sector_3": [
            2048,
            2048,
            2048,
            2048,
            2048,
            2048,
            2048,
            2048
        ],
        "lap_number": 10
    },
    {
        "meeting_key": 1259,
        "session_key": 10033,
        "driver_number": 12,
        "i1_speed": 206,
        "i2_speed": 179,
        "st_speed": 318,
        "date_start": "2025-05-04T20:20:08.003000+00:00",
        "lap_duration": 92.79,
        "is_pit_out_lap": false,
        "duration_sector_1": 31.515,
        "duration_sector_2": 35.098,
        "duration_sector_3": 26.177,
        "segments_sector_1": [
            null,
            2048,
            2048,
            2048,
            2048,
            2048,
            2048,
            2048,
            2048
        ],
        "segments_sector_2": [
            2048,
            2048,
            2048,
            2048,
            2048,
            2048,
            2048,
            2049,
            2048
        ],
        "segments_sector_3": [
            2048,
            2048,
            2048,
            2048,
            2048,
            2048,
            2048,
            2048
        ],
        "lap_number": 11
    },
    {
        "meeting_key": 1259,
        "session_key": 10033,
        "driver_number": 12,
        "i1_speed": 204,
        "i2_speed": 180,
        "st_speed": 317,
        "date_start": "2025-05-04T20:21:40.913000+00:00",
        "lap_duration": 92.725,
        "is_pit_out_lap": false,
        "duration_sector_1": 31.312,
        "duration_sector_2": 35.206,
        "duration_sector_3": 26.207,
        "segments_sector_1": [
            null,
            2048,
            2048,
            2048,
            2048,
            2049,
            2048,
            2048,
            2048
        ],
        "segments_sector_2": [
            2048,
            2048,
            2048,
            2048,
            2048,
            2048,
            2048,
            2048,
            2048
        ],
        "segments_sector_3": [
            2048,
            2048,
            2048,
            2048,
            2048,
            2048,
            2049,
            2048
        ],
        "lap_number": 12
    },
    {
        "meeting_key": 1259,
        "session_key": 10033,
        "driver_number": 12,
        "i1_speed": null,
        "i2_speed": 181,
        "st_speed": 314,
        "date_start": "2025-05-04T20:23:13.616000+00:00",
        "lap_duration": 92.745,
        "is_pit_out_lap": false,
        "duration_sector_1": 31.467,
        "duration_sector_2": 35.105,
        "duration_sector_3": 26.173,
        "segments_sector_1": [
            null,
            2048,
            2048,
            2048,
            2048,
            2048,
            2049,
            2048,
            2048
        ],
        "segments_sector_2": [
            2048,
            2048,
            2048,
            2048,
            2048,
            2048,
            2048,
            2048,
            2048
        ],
        "segments_sector_3": [
            2048,
            2048,
            2048,
            2048,
            2048,
            2048,
            2049,
            2048
        ],
        "lap_number": 13
    },
    {
        "meeting_key": 1259,
        "session_key": 10033,
        "driver_number": 12,
        "i1_speed": 205,
        "i2_speed": 181,
        "st_speed": 316,
        "date_start": "2025-05-04T20:24:46.368000+00:00",
        "lap_duration": 92.692,
        "is_pit_out_lap": false,
        "duration_sector_1": 31.517,
        "duration_sector_2": 35.038,
        "duration_sector_3": 26.137,
        "segments_sector_1": [
            null,
            2048,
            2048,
            2048,
            2048,
            2048,
            2049,
            2048,
            2048
        ],
        "segments_sector_2": [
            2048,
            2048,
            2048,
            2048,
            2048,
            2049,
            2048,
            2048,
            2048
        ],
        "segments_sector_3": [
            2048,
            2048,
            2048,
            2048,
            2048,
            2048,
            2049,
            2048
        ],
        "lap_number": 14
    },
    {
        "meeting_key": 1259,
        "session_key": 10033,
        "driver_number": 12,
        "i1_speed": 208,
        "i2_speed": 181,
        "st_speed": 312,
        "date_start": "2025-05-04T20:26:18.956000+00:00",
        "lap_duration": 92.902,
        "is_pit_out_lap": false,
        "duration_sector_1": 31.43,
        "duration_sector_2": 35.278,
        "duration_sector_3": 26.194,
        "segments_sector_1": [
            null,
            2048,
            2048,
            2048,
            2048,
            2048,
            2048,
            2048,
            2048
        ],
        "segments_sector_2": [
            2049,
            2048,
            2048,
            2048,
            2048,
            2048,
            2048,
            2048,
            2048
        ],
        "segments_sector_3": [
            0,
            0,
            0,
            0,
            2048,
            2048,
            2049,
            2048
        ],
        "lap_number": 15
    },
    {
        "meeting_key": 1259,
        "session_key": 10033,
        "driver_number": 12,
        "i1_speed": null,
        "i2_speed": null,
        "st_speed": null,
        "date_start": "2025-05-04T20:27:51.844000+00:00",
        "lap_duration": 92.4,
        "is_pit_out_lap": false,
        "duration_sector_1": null,
        "duration_sector_2": null,
        "duration_sector_3": 25.972,
        "segments_sector_1": [
            null,
            2048,
            2048,
            0,
            0,
            0,
            0,
            0,
            0
        ],
        "segments_sector_2": [
            0,
            0,
            0,
            0,
            0,
            0,
            0,
            0,
            0
        ],
        "segments_sector_3": [
            2048,
            2048,
            2048,
            2048,
            2048,
            2048,
            2049,
            2048
        ],
        "lap_number": 16
    },
    {
        "meeting_key": 1259,
        "session_key": 10033,
        "driver_number": 12,
        "i1_speed": 209,
        "i2_speed": 182,
        "st_speed": 315,
        "date_start": "2025-05-04T20:40:14.446000+00:00",
        "lap_duration": 92.5,
        "is_pit_out_lap": false,
        "duration_sector_1": 31.171,
        "duration_sector_2": 35.258,
        "duration_sector_3": 26.071,
        "segments_sector_1": [
            null,
            2048,
            2048,
            2048,
            2048,
            2049,
            2048,
            2048,
            2048
        ],
        "segments_sector_2": [
            2049,
            2048,
            2048,
            2048,
            2048,
            2048,
            2048,
            2048,
            2048
        ],
        "segments_sector_3": [
            2049,
            2048,
            2048,
            2048,
            2048,
            2048,
            2064,
            2064
        ],
        "lap_number": 17
    },
    {
        "meeting_key": 1259,
        "session_key": 10033,
        "driver_number": 12,
        "i1_speed": 208,
        "i2_speed": 183,
        "st_speed": 317,
        "date_start": "2025-05-04T20:41:46.934000+00:00",
        "lap_duration": 97.258,
        "is_pit_out_lap": false,
        "duration_sector_1": 31.087,
        "duration_sector_2": 35.379,
        "duration_sector_3": 30.792,
        "segments_sector_1": [
            null,
            2048,
            2048,
            2048,
            2048,
            2048,
            2048,
            2048,
            2048
        ],
        "segments_sector_2": [
            2048,
            2048,
            2048,
            2048,
            2048,
            2048,
            2048,
            2048,
            2048
        ],
        "segments_sector_3": [
            2049,
            2048,
            2048,
            2048,
            2051,
            2049,
            2049,
            2048
        ],
        "lap_number": 18
    },
    {
        "meeting_key": 1259,
        "session_key": 10033,
        "driver_number": 12,
        "i1_speed": 211,
        "i2_speed": 184,
        "st_speed": 316,
        "date_start": "2025-05-04T20:43:24.193000+00:00",
        "lap_duration": 108.147,
        "is_pit_out_lap": true,
        "duration_sector_1": 47.764,
        "duration_sector_2": 34.639,
        "duration_sector_3": 25.744,
        "segments_sector_1": [
            2064,
            2064,
            2064,
            2048,
            2048,
            2048,
            2049,
            2048,
            2049
        ],
        "segments_sector_2": [
            2049,
            2048,
            2048,
            2048,
            2048,
            2051,
            2049,
            2049,
            2049
        ],
        "segments_sector_3": [
            2049,
            2048,
            2048,
            2048,
            2048,
            2048,
            2049,
            2048
        ],
        "lap_number": 19
    },
    {
        "meeting_key": 1259,
        "session_key": 10033,
        "driver_number": 12,
        "i1_speed": 213,
        "i2_speed": 184,
        "st_speed": 317,
        "date_start": "2025-05-04T20:45:12.396000+00:00",
        "lap_duration": 90.795,
        "is_pit_out_lap": false,
        "duration_sector_1": 30.265,
        "duration_sector_2": 34.701,
        "duration_sector_3": 25.829,
        "segments_sector_1": [
            2048,
            2049,
            2049,
            2049,
            2049,
            2049,
            2049,
            2049,
            2049
        ],
        "segments_sector_2": [
            2049,
            2049,
            2048,
            2048,
            2048,
            2048,
            2048,
            2048,
            2048
        ],
        "segments_sector_3": [
            2049,
            2048,
            2048,
            2048,
            2048,
            2048,
            2048,
            2048
        ],
        "lap_number": 20
    },
    {
        "meeting_key": 1259,
        "session_key": 10033,
        "driver_number": 12,
        "i1_speed": 211,
        "i2_speed": 184,
        "st_speed": 317,
        "date_start": "2025-05-04T20:46:43.162000+00:00",
        "lap_duration": 97.71,
        "is_pit_out_lap": false,
        "duration_sector_1": 30.58,
        "duration_sector_2": 34.995,
        "duration_sector_3": 32.135,
        "segments_sector_1": [
            null,
            2048,
            2048,
            2048,
            2048,
            2048,
            2048,
            2049,
            2048
        ],
        "segments_sector_2": [
            2048,
            2048,
            2048,
            2048,
            2048,
            2048,
            2048,
            2048,
            2048
        ],
        "segments_sector_3": [
            2048,
            2048,
            2048,
            2048,
            2048,
            2048,
            2048,
            2048
        ],
        "lap_number": 21
    },
    {
        "meeting_key": 1259,
        "session_key": 10033,
        "driver_number": 12,
        "i1_speed": 144,
        "i2_speed": 120,
        "st_speed": 187,
        "date_start": "2025-05-04T20:48:20.794000+00:00",
        "lap_duration": 124.85,
        "is_pit_out_lap": false,
        "duration_sector_1": 41.317,
        "duration_sector_2": 48.906,
        "duration_sector_3": 34.627,
        "segments_sector_1": [
            null,
            2048,
            2048,
            2048,
            2048,
            2048,
            2048,
            2048,
            2048
        ],
        "segments_sector_2": [
            2048,
            2048,
            2048,
            2048,
            2048,
            2048,
            2048,
            2048,
            2048
        ],
        "segments_sector_3": [
            2049,
            2048,
            2048,
            2048,
            2048,
            2049,
            2048,
            2048
        ],
        "lap_number": 22
    },
    {
        "meeting_key": 1259,
        "session_key": 10033,
        "driver_number": 12,
        "i1_speed": 212,
        "i2_speed": 186,
        "st_speed": 319,
        "date_start": "2025-05-04T20:50:25.674000+00:00",
        "lap_duration": 91.786,
        "is_pit_out_lap": false,
        "duration_sector_1": 31.088,
        "duration_sector_2": 34.695,
        "duration_sector_3": 26.003,
        "segments_sector_1": [
            null,
            2048,
            2048,
            2049,
            2049,
            2048,
            2048,
            2048,
            2048
        ],
        "segments_sector_2": [
            2048,
            2048,
            2048,
            2048,
            2048,
            2048,
            2049,
            2048,
            2049
        ],
        "segments_sector_3": [
            2048,
            2049,
            2048,
            2049,
            2048,
            2048,
            2049,
            2048
        ],
        "lap_number": 23
    },
    {
        "meeting_key": 1259,
        "session_key": 10033,
        "driver_number": 12,
        "i1_speed": 210,
        "i2_speed": 183,
        "st_speed": 319,
        "date_start": "2025-05-04T20:51:57.465000+00:00",
        "lap_duration": 92.717,
        "is_pit_out_lap": false,
        "duration_sector_1": 31.783,
        "duration_sector_2": 35.07,
        "duration_sector_3": 25.864,
        "segments_sector_1": [
            null,
            2049,
            2048,
            2048,
            2048,
            2048,
            2048,
            2048,
            2048
        ],
        "segments_sector_2": [
            2048,
            2049,
            2049,
            2049,
            2048,
            2048,
            2048,
            2048,
            2048
        ],
        "segments_sector_3": [
            2048,
            2048,
            2048,
            2048,
            2048,
            2048,
            2049,
            2048
        ],
        "lap_number": 24
    },
    {
        "meeting_key": 1259,
        "session_key": 10033,
        "driver_number": 12,
        "i1_speed": 209,
        "i2_speed": 180,
        "st_speed": 309,
        "date_start": "2025-05-04T20:53:30.131000+00:00",
        "lap_duration": 91.967,
        "is_pit_out_lap": false,
        "duration_sector_1": 30.998,
        "duration_sector_2": 34.98,
        "duration_sector_3": 25.989,
        "segments_sector_1": [
            null,
            2048,
            2048,
            2048,
            2048,
            2048,
            2048,
            2048,
            2048
        ],
        "segments_sector_2": [
            2048,
            2048,
            2048,
            2048,
            2048,
            2048,
            2048,
            2048,
            2048
        ],
        "segments_sector_3": [
            2048,
            2048,
            2048,
            2048,
            2048,
            2048,
            2048,
            2048
        ],
        "lap_number": 25
    },
    {
        "meeting_key": 1259,
        "session_key": 10033,
        "driver_number": 12,
        "i1_speed": 141,
        "i2_speed": 99,
        "st_speed": 279,
        "date_start": "2025-05-04T20:55:02.303000+00:00",
        "lap_duration": 119.776,
        "is_pit_out_lap": false,
        "duration_sector_1": 41.226,
        "duration_sector_2": 48.688,
        "duration_sector_3": 29.862,
        "segments_sector_1": [
            null,
            2048,
            2048,
            2048,
            2048,
            2048,
            2048,
            2048,
            2048
        ],
        "segments_sector_2": [
            2048,
            2048,
            2048,
            2048,
            2048,
            2048,
            2048,
            2048,
            2048
        ],
        "segments_sector_3": [
            2048,
            2048,
            2048,
            2048,
            2048,
            2048,
            2048,
            2048
        ],
        "lap_number": 26
    },
    {
        "meeting_key": 1259,
        "session_key": 10033,
        "driver_number": 12,
        "i1_speed": 211,
        "i2_speed": 183,
        "st_speed": 316,
        "date_start": "2025-05-04T20:57:01.951000+00:00",
        "lap_duration": 90.845,
        "is_pit_out_lap": false,
        "duration_sector_1": 30.434,
        "duration_sector_2": 34.608,
        "duration_sector_3": 25.803,
        "segments_sector_1": [
            null,
            2048,
            2048,
            2048,
            2049,
            2048,
            2048,
            2048,
            2048
        ],
        "segments_sector_2": [
            2048,
            2048,
            2048,
            2048,
            2049,
            2048,
            2048,
            2048,
            2048
        ],
        "segments_sector_3": [
            2048,
            2049,
            2048,
            2048,
            2048,
            2048,
            2048,
            2049
        ],
        "lap_number": 27
    },
    {
        "meeting_key": 1259,
        "session_key": 10033,
        "driver_number": 12,
        "i1_speed": 213,
        "i2_speed": 183,
        "st_speed": 317,
        "date_start": "2025-05-04T20:58:32.894000+00:00",
        "lap_duration": 90.807,
        "is_pit_out_lap": false,
        "duration_sector_1": 30.328,
        "duration_sector_2": 34.762,
        "duration_sector_3": 25.717,
        "segments_sector_1": [
            null,
            2048,
            2049,
            2048,
            2049,
            2048,
            2048,
            2048,
            2048
        ],
        "segments_sector_2": [
            2049,
            2049,
            2048,
            2048,
            2048,
            2048,
            2048,
            2048,
            2048
        ],
        "segments_sector_3": [
            2048,
            2048,
            2048,
            2048,
            2048,
            2048,
            2049,
            2049
        ],
        "lap_number": 28
    },
    {
        "meeting_key": 1259,
        "session_key": 10033,
        "driver_number": 12,
        "i1_speed": 210,
        "i2_speed": 183,
        "st_speed": 317,
        "date_start": "2025-05-04T21:00:03.695000+00:00",
        "lap_duration": 90.948,
        "is_pit_out_lap": false,
        "duration_sector_1": 30.419,
        "duration_sector_2": 34.798,
        "duration_sector_3": 25.731,
        "segments_sector_1": [
            null,
            2048,
            2048,
            2048,
            2049,
            2048,
            2048,
            2048,
            2048
        ],
        "segments_sector_2": [
            2048,
            2048,
            2048,
            2048,
            2048,
            2048,
            2048,
            2048,
            2048
        ],
        "segments_sector_3": [
            2048,
            2048,
            2048,
            2048,
            2048,
            2048,
            2048,
            2048
        ],
        "lap_number": 29
    },
    {
        "meeting_key": 1259,
        "session_key": 10033,
        "driver_number": 12,
        "i1_speed": 213,
        "i2_speed": 180,
        "st_speed": 317,
        "date_start": "2025-05-04T21:01:34.578000+00:00",
        "lap_duration": 91.352,
        "is_pit_out_lap": false,
        "duration_sector_1": 30.445,
        "duration_sector_2": 35.032,
        "duration_sector_3": 25.875,
        "segments_sector_1": [
            null,
            2048,
            2048,
            2048,
            2048,
            2048,
            2048,
            2048,
            2048
        ],
        "segments_sector_2": [
            2049,
            2049,
            2049,
            2049,
            2048,
            2048,
            2048,
            2048,
            2048
        ],
        "segments_sector_3": [
            2048,
            2048,
            2048,
            2048,
            2048,
            2048,
            2048,
            2048
        ],
        "lap_number": 30
    },
    {
        "meeting_key": 1259,
        "session_key": 10033,
        "driver_number": 12,
        "i1_speed": 212,
        "i2_speed": 182,
        "st_speed": 319,
        "date_start": "2025-05-04T21:03:05.912000+00:00",
        "lap_duration": 91.086,
        "is_pit_out_lap": false,
        "duration_sector_1": 30.413,
        "duration_sector_2": 34.804,
        "duration_sector_3": 25.869,
        "segments_sector_1": [
            null,
            2048,
            2048,
            2048,
            2048,
            2048,
            2049,
            2048,
            2048
        ],
        "segments_sector_2": [
            2048,
            2048,
            2048,
            2049,
            2048,
            2048,
            2048,
            2048,
            2048
        ],
        "segments_sector_3": [
            2048,
            2048,
            2048,
            2048,
            2048,
            2048,
            2048,
            2048
        ],
        "lap_number": 31
    },
    {
        "meeting_key": 1259,
        "session_key": 10033,
        "driver_number": 12,
        "i1_speed": 209,
        "i2_speed": 183,
        "st_speed": 316,
        "date_start": "2025-05-04T21:04:37.041000+00:00",
        "lap_duration": 91.188,
        "is_pit_out_lap": false,
        "duration_sector_1": 30.44,
        "duration_sector_2": 34.9,
        "duration_sector_3": 25.848,
        "segments_sector_1": [
            null,
            2048,
            2048,
            2048,
            2048,
            2048,
            2048,
            2048,
            2048
        ],
        "segments_sector_2": [
            2048,
            2048,
            2048,
            2048,
            2048,
            2048,
            2048,
            2048,
            2048
        ],
        "segments_sector_3": [
            2048,
            2048,
            2048,
            2049,
            2048,
            2048,
            2048,
            2048
        ],
        "lap_number": 32
    },
    {
        "meeting_key": 1259,
        "session_key": 10033,
        "driver_number": 12,
        "i1_speed": 210,
        "i2_speed": 181,
        "st_speed": 320,
        "date_start": "2025-05-04T21:06:08.260000+00:00",
        "lap_duration": 91.288,
        "is_pit_out_lap": false,
        "duration_sector_1": 30.505,
        "duration_sector_2": 34.965,
        "duration_sector_3": 25.818,
        "segments_sector_1": [
            null,
            2048,
            2048,
            2048,
            2048,
            2048,
            2048,
            2048,
            2048
        ],
        "segments_sector_2": [
            2048,
            2048,
            2048,
            2049,
            2048,
            2048,
            2048,
            2048,
            2048
        ],
        "segments_sector_3": [
            2048,
            2048,
            2048,
            2048,
            2048,
            2048,
            2048,
            2048
        ],
        "lap_number": 33
    },
    {
        "meeting_key": 1259,
        "session_key": 10033,
        "driver_number": 12,
        "i1_speed": null,
        "i2_speed": 182,
        "st_speed": 316,
        "date_start": "2025-05-04T21:07:39.521000+00:00",
        "lap_duration": 91.58,
        "is_pit_out_lap": false,
        "duration_sector_1": 30.706,
        "duration_sector_2": 34.998,
        "duration_sector_3": 25.876,
        "segments_sector_1": [
            null,
            2048,
            2048,
            2048,
            2048,
            2048,
            0,
            0,
            0
        ],
        "segments_sector_2": [
            0,
            0,
            0,
            0,
            0,
            2048,
            2048,
            2048,
            2048
        ],
        "segments_sector_3": [
            2048,
            2048,
            2048,
            2048,
            2048,
            2048,
            2049,
            2048
        ],
        "lap_number": 34
    },
    {
        "meeting_key": 1259,
        "session_key": 10033,
        "driver_number": 12,
        "i1_speed": null,
        "i2_speed": 180,
        "st_speed": 314,
        "date_start": "2025-05-04T21:10:42.781000+00:00",
        "lap_duration": 91.616,
        "is_pit_out_lap": false,
        "duration_sector_1": 30.666,
        "duration_sector_2": 35.119,
        "duration_sector_3": 25.831,
        "segments_sector_1": [
            null,
            2048,
            2048,
            2048,
            2048,
            2048,
            2048,
            2048,
            2048
        ],
        "segments_sector_2": [
            2048,
            2048,
            2048,
            2048,
            2048,
            2048,
            2048,
            2048,
            2048
        ],
        "segments_sector_3": [
            2049,
            2048,
            2048,
            2048,
            2048,
            2048,
            2048,
            2048
        ],
        "lap_number": 35
    },
    {
        "meeting_key": 1259,
        "session_key": 10033,
        "driver_number": 12,
        "i1_speed": 209,
        "i2_speed": 184,
        "st_speed": 313,
        "date_start": "2025-05-04T21:12:14.400000+00:00",
        "lap_duration": 91.187,
        "is_pit_out_lap": false,
        "duration_sector_1": 30.47,
        "duration_sector_2": 34.892,
        "duration_sector_3": 25.825,
        "segments_sector_1": [
            null,
            2048,
            2048,
            2048,
            2048,
            2048,
            2048,
            2048,
            2048
        ],
        "segments_sector_2": [
            2048,
            2048,
            2048,
            2048,
            2048,
            2048,
            2048,
            2048,
            2048
        ],
        "segments_sector_3": [
            2048,
            2048,
            2048,
            2048,
            2048,
            2048,
            2048,
            2048
        ],
        "lap_number": 36
    },
    {
        "meeting_key": 1259,
        "session_key": 10033,
        "driver_number": 12,
        "i1_speed": 210,
        "i2_speed": 183,
        "st_speed": 320,
        "date_start": "2025-05-04T21:13:45.497000+00:00",
        "lap_duration": 91.426,
        "is_pit_out_lap": false,
        "duration_sector_1": 30.583,
        "duration_sector_2": 35.017,
        "duration_sector_3": 25.826,
        "segments_sector_1": [
            null,
            2048,
            2048,
            2048,
            2048,
            2048,
            2048,
            2048,
            2048
        ],
        "segments_sector_2": [
            2048,
            2048,
            2048,
            2048,
            2048,
            2048,
            2048,
            2048,
            2048
        ],
        "segments_sector_3": [
            2048,
            2048,
            2048,
            2049,
            2048,
            2048,
            2048,
            2049
        ],
        "lap_number": 37
    },
    {
        "meeting_key": 1259,
        "session_key": 10033,
        "driver_number": 12,
        "i1_speed": null,
        "i2_speed": 185,
        "st_speed": 318,
        "date_start": "2025-05-04T21:15:16.986000+00:00",
        "lap_duration": 91.572,
        "is_pit_out_lap": false,
        "duration_sector_1": 30.799,
        "duration_sector_2": 34.933,
        "duration_sector_3": 25.84,
        "segments_sector_1": [
            null,
            2048,
            2048,
            2048,
            2048,
            2048,
            2049,
            2048,
            2048
        ],
        "segments_sector_2": [
            2048,
            2048,
            2048,
            2048,
            2048,
            2048,
            2048,
            2048,
            2048
        ],
        "segments_sector_3": [
            2049,
            2048,
            2048,
            2048,
            2048,
            2048,
            2049,
            2049
        ],
        "lap_number": 38
    },
    {
        "meeting_key": 1259,
        "session_key": 10033,
        "driver_number": 12,
        "i1_speed": 211,
        "i2_speed": 185,
        "st_speed": 315,
        "date_start": "2025-05-04T21:16:48.561000+00:00",
        "lap_duration": 91.375,
        "is_pit_out_lap": false,
        "duration_sector_1": 30.588,
        "duration_sector_2": 34.941,
        "duration_sector_3": 25.846,
        "segments_sector_1": [
            null,
            2048,
            2048,
            2048,
            2048,
            2048,
            2048,
            2048,
            2048
        ],
        "segments_sector_2": [
            2048,
            2048,
            2048,
            2048,
            2048,
            2048,
            2048,
            2048,
            2048
        ],
        "segments_sector_3": [
            2049,
            2048,
            2048,
            2048,
            2048,
            2048,
            2048,
            2049
        ],
        "lap_number": 39
    },
    {
        "meeting_key": 1259,
        "session_key": 10033,
        "driver_number": 12,
        "i1_speed": null,
        "i2_speed": 185,
        "st_speed": 318,
        "date_start": "2025-05-04T21:18:19.989000+00:00",
        "lap_duration": 91.072,
        "is_pit_out_lap": false,
        "duration_sector_1": 30.452,
        "duration_sector_2": 34.925,
        "duration_sector_3": 25.695,
        "segments_sector_1": [
            null,
            2048,
            2048,
            2048,
            2048,
            2048,
            2048,
            2048,
            2048
        ],
        "segments_sector_2": [
            2048,
            2048,
            2048,
            2048,
            2048,
            2048,
            2048,
            2048,
            2048
        ],
        "segments_sector_3": [
            2049,
            2048,
            2048,
            2048,
            2048,
            2048,
            2049,
            2049
        ],
        "lap_number": 40
    },
    {
        "meeting_key": 1259,
        "session_key": 10033,
        "driver_number": 12,
        "i1_speed": null,
        "i2_speed": 185,
        "st_speed": 318,
        "date_start": "2025-05-04T21:19:50.974000+00:00",
        "lap_duration": 91.131,
        "is_pit_out_lap": false,
        "duration_sector_1": 30.554,
        "duration_sector_2": 34.819,
        "duration_sector_3": 25.758,
        "segments_sector_1": [
            null,
            2048,
            2048,
            2048,
            2049,
            2048,
            2048,
            2048,
            2048
        ],
        "segments_sector_2": [
            2048,
            2048,
            2048,
            2048,
            2048,
            2048,
            2048,
            2048,
            2048
        ],
        "segments_sector_3": [
            2049,
            2048,
            2048,
            2048,
            2048,
            2048,
            2049,
            2049
        ],
        "lap_number": 41
    },
    {
        "meeting_key": 1259,
        "session_key": 10033,
        "driver_number": 12,
        "i1_speed": null,
        "i2_speed": 186,
        "st_speed": 316,
        "date_start": "2025-05-04T21:21:22.159000+00:00",
        "lap_duration": 90.946,
        "is_pit_out_lap": false,
        "duration_sector_1": 30.369,
        "duration_sector_2": 34.815,
        "duration_sector_3": 25.762,
        "segments_sector_1": [
            null,
            2048,
            2048,
            2048,
            2048,
            2048,
            2049,
            2049,
            2048
        ],
        "segments_sector_2": [
            2048,
            2048,
            2048,
            2048,
            2048,
            2048,
            2048,
            2048,
            2048
        ],
        "segments_sector_3": [
            2049,
            2048,
            2048,
            2048,
            2048,
            2048,
            2048,
            2048
        ],
        "lap_number": 42
    },
    {
        "meeting_key": 1259,
        "session_key": 10033,
        "driver_number": 12,
        "i1_speed": null,
        "i2_speed": 186,
        "st_speed": 317,
        "date_start": "2025-05-04T21:22:53.037000+00:00",
        "lap_duration": 90.965,
        "is_pit_out_lap": false,
        "duration_sector_1": 30.366,
        "duration_sector_2": 34.841,
        "duration_sector_3": 25.758,
        "segments_sector_1": [
            null,
            2048,
            2048,
            2048,
            2049,
            2048,
            2049,
            2048,
            2048
        ],
        "segments_sector_2": [
            2048,
            2048,
            2048,
            2048,
            2048,
            2048,
            2048,
            2048,
            2048
        ],
        "segments_sector_3": [
            2048,
            2048,
            2048,
            2048,
            2048,
            2048,
            2048,
            2048
        ],
        "lap_number": 43
    },
    {
        "meeting_key": 1259,
        "session_key": 10033,
        "driver_number": 12,
        "i1_speed": 212,
        "i2_speed": 186,
        "st_speed": 315,
        "date_start": "2025-05-04T21:24:24.085000+00:00",
        "lap_duration": 90.973,
        "is_pit_out_lap": false,
        "duration_sector_1": 30.432,
        "duration_sector_2": 34.726,
        "duration_sector_3": 25.815,
        "segments_sector_1": [
            null,
            2048,
            2048,
            2048,
            2048,
            2048,
            2048,
            2048,
            2048
        ],
        "segments_sector_2": [
            2048,
            2048,
            2048,
            2048,
            2048,
            2048,
            2048,
            2048,
            2048
        ],
        "segments_sector_3": [
            2048,
            2048,
            2048,
            2048,
            2048,
            2048,
            2048,
            2048
        ],
        "lap_number": 44
    },
    {
        "meeting_key": 1259,
        "session_key": 10033,
        "driver_number": 12,
        "i1_speed": null,
        "i2_speed": 185,
        "st_speed": 315,
        "date_start": "2025-05-04T21:25:55.008000+00:00",
        "lap_duration": 90.988,
        "is_pit_out_lap": false,
        "duration_sector_1": 30.307,
        "duration_sector_2": 34.885,
        "duration_sector_3": 25.796,
        "segments_sector_1": [
            null,
            2048,
            2048,
            2049,
            2049,
            2048,
            2049,
            2048,
            2048
        ],
        "segments_sector_2": [
            2049,
            2048,
            2048,
            2048,
            2048,
            2048,
            2048,
            2048,
            2048
        ],
        "segments_sector_3": [
            2048,
            2048,
            2048,
            2049,
            2048,
            2048,
            2048,
            2048
        ],
        "lap_number": 45
    },
    {
        "meeting_key": 1259,
        "session_key": 10033,
        "driver_number": 12,
        "i1_speed": null,
        "i2_speed": 185,
        "st_speed": 318,
        "date_start": "2025-05-04T21:27:25.955000+00:00",
        "lap_duration": 90.912,
        "is_pit_out_lap": false,
        "duration_sector_1": 30.244,
        "duration_sector_2": 34.894,
        "duration_sector_3": 25.774,
        "segments_sector_1": [
            null,
            2048,
            2048,
            2048,
            2048,
            2049,
            2049,
            2048,
            2048
        ],
        "segments_sector_2": [
            2048,
            2048,
            2048,
            2048,
            2048,
            2048,
            2048,
            2048,
            2048
        ],
        "segments_sector_3": [
            2049,
            2048,
            2048,
            2048,
            2048,
            2048,
            2049,
            2048
        ],
        "lap_number": 46
    },
    {
        "meeting_key": 1259,
        "session_key": 10033,
        "driver_number": 12,
        "i1_speed": 211,
        "i2_speed": 186,
        "st_speed": 315,
        "date_start": "2025-05-04T21:28:56.978000+00:00",
        "lap_duration": 90.829,
        "is_pit_out_lap": false,
        "duration_sector_1": 30.274,
        "duration_sector_2": 34.846,
        "duration_sector_3": 25.709,
        "segments_sector_1": [
            null,
            2048,
            2048,
            2048,
            2049,
            2048,
            2048,
            2048,
            2048
        ],
        "segments_sector_2": [
            2048,
            2048,
            2048,
            2048,
            2048,
            2048,
            2048,
            2048,
            2048
        ],
        "segments_sector_3": [
            2048,
            2048,
            2048,
            2048,
            2048,
            2048,
            2048,
            2048
        ],
        "lap_number": 47
    },
    {
        "meeting_key": 1259,
        "session_key": 10033,
        "driver_number": 12,
        "i1_speed": 213,
        "i2_speed": 186,
        "st_speed": 317,
        "date_start": "2025-05-04T21:30:27.849000+00:00",
        "lap_duration": 90.937,
        "is_pit_out_lap": false,
        "duration_sector_1": 30.27,
        "duration_sector_2": 34.893,
        "duration_sector_3": 25.774,
        "segments_sector_1": [
            null,
            2048,
            2048,
            2048,
            2048,
            2048,
            2049,
            2048,
            2048
        ],
        "segments_sector_2": [
            2049,
            2049,
            2048,
            2048,
            2048,
            2048,
            2048,
            2048,
            2048
        ],
        "segments_sector_3": [
            2048,
            2049,
            2048,
            2048,
            2048,
            2049,
            2049,
            2048
        ],
        "lap_number": 48
    },
    {
        "meeting_key": 1259,
        "session_key": 10033,
        "driver_number": 12,
        "i1_speed": 212,
        "i2_speed": 184,
        "st_speed": 314,
        "date_start": "2025-05-04T21:31:58.653000+00:00",
        "lap_duration": 90.999,
        "is_pit_out_lap": false,
        "duration_sector_1": 30.299,
        "duration_sector_2": 34.955,
        "duration_sector_3": 25.745,
        "segments_sector_1": [
            null,
            2048,
            2048,
            2048,
            2048,
            2049,
            2048,
            2048,
            2048
        ],
        "segments_sector_2": [
            2049,
            2049,
            2049,
            2048,
            2048,
            2048,
            2048,
            2048,
            2048
        ],
        "segments_sector_3": [
            0,
            0,
            0,
            0,
            0,
            0,
            0,
            0
        ],
        "lap_number": 49
    }
]